{
    "projects": [
        {
            "name": "EMPTY PROJECT",
            "image": "empty.png",
            "desc": "An empty canvas for you to create your games upon",
            "type": "Himawari default",
            "clone": ""
        },
        {
            "name": "2D PLATFORMER",
            "image": "platformer.png",
            "desc": "Creates a little game set up with 2D physics and platforming movement",
            "type": "Himawari default",
            "clone": ""
        },
        {
            "name": "TOP DOWN RPG",
            "image": "topdown.png",
            "desc": "Creates a game set up with bidimensional movement, a camera, and a map",
            "type": "Himawari default",
            "clone": ""
        },
        {
            "name": "PONG!",
            "image": "pong.png",
            "desc": "Imports the complete Pong game template",
            "type": "Himawari templates",
            "clone": ""
        },
        {
            "name": "StepMania",
            "image": "sm.png",
            "desc": "Imports the complete StepMania game template",
            "type": "Himawari templates",
            "clone": ""
        },
        {
            "name": "Mario",
            "image": "mario.png",
            "desc": "Imports the complete Mario game template",
            "type": "Himawari templates",
            "clone": ""
        },
        {
            "name": "Touhou",
            "image": "touhou.png",
            "desc": "Imports the complete Touhou game template",
            "type": "Himawari templates",
            "clone": ""
        }
    ]
}